{"content":"{\n    \"data\": {\n        \"id\": 75,\n        \"belong_id\": 0,\n        \"name\": \"\u56db\u53f6\u8349\",\n        \"api_token\": null,\n        \"first_site\": \"1\",\n        \"ip\": \"\",\n        \"phone\": \"13628037661\",\n        \"email\": \"123456@163.com\",\n        \"openid\": \"\",\n        \"uniqueid\": \"\",\n        \"created_at\": \"2018-10-29 10:20:41\",\n        \"updated_at\": \"2018-10-29 10:58:10\",\n        \"invite_code\": \"42cb\",\n        \"user_source\": null\n    },\n    \"status\": 1,\n    \"code\": 200,\n    \"msg\": \"\u4fee\u6539\u6210\u529f\"\n}","time":1540781890,"action":"App\\Http\\Controllers\\Api\\User\\SessionController@forgetPwd","url":"api\/user\/session\/forget_password"}